hello_gfw-0.0.1.dist-info/DESCRIPTION.rst
hello_gfw-0.0.1.dist-info/METADATA
hello_gfw-0.0.1.dist-info/metadata.json
hello_gfw-0.0.1.dist-info/RECORD
hello_gfw-0.0.1.dist-info/top_level.txt
hello_gfw-0.0.1.dist-info/WHEEL
hgfw/__init__.py
hgfw/default.dict
