Metadata-Version: 2.0
Name: hello-gfw
Version: 0.0.1
Summary: A simple text filter for GFW friendly UGC applications.
Home-page: https://github.com/microdog/hello-gfw
Author: Microdog
Author-email: dlangu0393@gmail.com
License: MIT
Keywords: gfw filter
Platform: UNKNOWN
Classifier: Development Status :: 3 - Alpha
Classifier: Intended Audience :: Developers
Classifier: Topic :: Software Development :: Libraries
Classifier: License :: OSI Approved :: MIT License
Classifier: Programming Language :: Python :: 2
Classifier: Programming Language :: Python :: 2.6
Classifier: Programming Language :: Python :: 2.7
Requires-Dist: DAWG
Provides-Extra: test
Requires-Dist: coverage; extra == 'test'
Provides-Extra: dev
Requires-Dist: check-manifest; extra == 'dev'
